{
  "rcept_no": "20251106000042",
  "corp_name": "LK삼양",
  "corp_code": "00992543",
  "stock_code": "225190",
  "market": "KOSDAQ",
  "status": "청약예정",
  "dart_link": "https://dart.fss.or.kr/dsaf001/main.do?rcpNo=20251106000042",
  "offering_price_low": "",
  "offering_price_high": "",
  "offering_price_final": "",
  "subscription_start_dt": "",
  "subscription_end_dt": "",
  "listing_dt": "",
  "underwriter": "",
  "total_shares": "",
  "competition_ratio": "",
  "lock_up_ratio": "",
  "demand_forecast_period": "",
  "business_summary": "",
  "news": [
    {
      "title": "[속보] LK삼양 주가 상한가 도달…'최근 큰폭의 변동' - CBC뉴스",
      "link": "https://news.google.com/rss/articles/CBMiaEFVX3lxTE00bnowTmhvR1NfbTMzZ2tXd0xpSjU1eFJGUDgzaVFNejVDdi1iRDZNLUVnZWtEclhUcmxmRS0zczhMcVp6SFRDR2hYQk8xU0hBOE1kOFRXVWhhcDI2cWdTYzVaX3pLN1BE?oc=5",
      "pubDate": "Fri, 06 Feb 2026 08:00:00 GMT"
    }
  ],
  "community_news": [
    {
      "title": "[주식마감] '스페이스X' 상장 기대에 미래에셋벤투·아주IB 상한가... '광...",
      "link": "https://www.ggilbo.com/news/articleView.html?idxno=1152732",
      "description": "미래에셋증권이 약 50억달러 규모의 <b>공모</b> 물량을 확보해 국내 투자자들에게 직접 투자 길을 열고... 쏠리드, <b>LK삼양</b>, 썸에이지, 캡스톤파트너스다. 이날 코스피는 전장보다 159.13포인트(2.74%) 상승한 5,967.75에 거래를... ",
      "pubDate": "Tue, 14 Apr 2026 19:40:00 +0900",
      "source": "뉴스"
    },
    {
      "title": "[주식마감] 현대차 강세에 계양전기 상한가... 참엔지니어링, 서울반도...",
      "link": "https://www.ggilbo.com/news/articleView.html?idxno=1143641",
      "description": "이는 씨엔플러스가 지난해 흑자 전환이라는 호실적을 발표한 데 이어, 일반<b>공모</b> 유상증자까지 초과... 대한광통신, <b>LK삼양</b>, SKAI, 비엘팜텍, 위더스제약, 지아이텍, 우리기술, 빌리언스, 모베이스, 원풍물산... ",
      "pubDate": "Wed, 25 Feb 2026 19:56:00 +0900",
      "source": "뉴스"
    },
    {
      "title": "12월 23일 주식시장 주요공시",
      "link": "https://www.catchnews.kr/news/articleView.html?idxno=118705",
      "description": "40억원) 규모 주주배정후 실권주 일반<b>공모</b> 유상증자 결정(예정발행가:2,810원,1주당 약 0.74주 배정... 81억원 규모 유형자산(토지 및 건물) 양수 결정 철회 ▶네패스, 공매도 과열종목 지정 ▶<b>LK삼양</b>... ",
      "pubDate": "Wed, 24 Dec 2025 08:48:00 +0900",
      "source": "뉴스"
    },
    {
      "title": "우주항공산업 관련주, '봄날의 햇살' 에이치브이엠·태웅·한화시스템·...",
      "link": "http://www.finomy.com/news/articleView.html?idxno=245338",
      "description": "한국항공우주, <b>LK삼양</b>은 상승했다. 스피어와 에이치브이엠은 전 거래일 대비 각각 1880원, 5000원 오른... 내년 기업공개(IPO) 목표에, 상장 시 기업가치와 <b>공모</b> 규모가 역사상 최대 수준에 이를 수 있다는 전망까지... ",
      "pubDate": "Sun, 14 Dec 2025 00:10:00 +0900",
      "source": "뉴스"
    },
    {
      "title": "오늘의 메모[12월 2일]",
      "link": "https://www.sedaily.com/NewsView/2H1K8G797N",
      "description": "▲보통주추가상장=키움증권(039490)(주식의종류변경) &lt;코스닥&gt; ▲<b>공모주</b>청약=페스카로·이지스... (185490) ▲보통주추가상장=<b>LK삼양</b>(225190)(유상) 한울소재과학(091440)(국내CB) 인투셀(287840)(신주인수권행사)... ",
      "pubDate": "Mon, 01 Dec 2025 10:33:00 +0900",
      "source": "뉴스"
    },
    {
      "title": "2026년4월27일 경제뉴스 신문기사 경제브리핑 보모보험",
      "link": "https://blog.naver.com/bomo4life/224266297820",
      "description": "석유화학 업계(LG화학, 롯데, OCI, <b>삼양</b>), 반도체 공정용 고부가 소재로 사업 중심 이동,,. 삼성카드... 통계 혼선 및 주요 <b>청약</b> 소식 서울 입주 물량 통계, 기관별 집계 기준 차이로 최대 3만 가구 격차 발생... ",
      "pubDate": "20260427",
      "source": "블로그"
    },
    {
      "title": "4월27일 종목브리핑(이노인스트루먼트,한양증권,노랑풍선)",
      "link": "https://blog.naver.com/joon854235/224266293928",
      "description": "OCI홀딩스,<b>LK삼양</b>) -광통신주가 빛과전자,광전자,우리로,이노인스트루먼트가 외봉 만들고 50%정도... 코스모로보틱스 <b>공모</b><b>청약</b> ✅영국 국왕 미국 국빈방문 ✅오픈베이스,APS이노베션이 단일가 해제일... ",
      "pubDate": "20260427",
      "source": "블로그"
    },
    {
      "title": "AI 웹툰, 피할 수 없는 물결!",
      "link": "https://blog.naver.com/joosiksin/224266289863",
      "description": "삼성화재해상보험 <b>삼양</b>식품 세아베스틸지주 세아제강 세아특수강 신세계 신세계I&amp;C... 삼성증권 <b>삼양</b>사 <b>삼양</b>홀딩스 삼호개발 삼화페인트공업 서연 서연이화 서흥 선진 세방 세아제강지주 세아홀딩스... ",
      "pubDate": "20260427",
      "source": "블로그"
    }
  ],
  "updated_at": "2026-04-26 23:59:59",
  "total_shares_offered": "",
  "min_bid_price": ""
}